collective.monkeypatcher-2.0.1-py3.13-nspkg.pth
collective/monkeypatcher/__init__.py
collective/monkeypatcher/configure.zcml
collective/monkeypatcher/interfaces.py
collective/monkeypatcher/meta.py
collective/monkeypatcher/meta.zcml
collective/monkeypatcher/tests/__init__.py
collective/monkeypatcher/tests/common.py
collective/monkeypatcher/tests/dummypatch.py
collective/monkeypatcher/tests/dummypatch.zcml
collective/monkeypatcher/tests/test_monkeypatcher.py
collective_monkeypatcher-2.0.1.dist-info/METADATA
collective_monkeypatcher-2.0.1.dist-info/WHEEL
collective_monkeypatcher-2.0.1.dist-info/namespace_packages.txt
collective_monkeypatcher-2.0.1.dist-info/top_level.txt
collective_monkeypatcher-2.0.1.dist-info/RECORD
