Metadata-Version: 2.4
Name: collective.monkeypatcher
Version: 2.0.1
Summary: Support for applying monkey patches late in the startup cycle by using ZCML configuration actions
Home-page: https://github.com/plone/collective.monkeypatcher
Author: Martin Aspeli
Author-email: optilude@gmail.com
License: BSD
Keywords: zope monkey patch
Classifier: Development Status :: 5 - Production/Stable
Classifier: License :: OSI Approved :: BSD License
Classifier: Programming Language :: Python
Classifier: Programming Language :: Python :: 3.9
Classifier: Programming Language :: Python :: 3.10
Classifier: Programming Language :: Python :: 3.11
Classifier: Programming Language :: Python :: 3.12
Classifier: Programming Language :: Python :: 3.13
Requires-Python: >=3.9
Requires-Dist: setuptools
Requires-Dist: zope.configuration
Requires-Dist: zope.event
Requires-Dist: zope.interface
Requires-Dist: zope.schema
Provides-Extra: test
Requires-Dist: zope.component; extra == "test"
Requires-Dist: zope.configuration; extra == "test"
Dynamic: author
Dynamic: author-email
Dynamic: classifier
Dynamic: description
Dynamic: home-page
Dynamic: keywords
Dynamic: license
Dynamic: provides-extra
Dynamic: requires-dist
Dynamic: requires-python
Dynamic: summary
